xlsx_creator-1.4.0.dist-info/licenses/LICENSE
xlsx_creator-1.4.0.dist-info/licenses/NOTICE
xlsxcreator/__init__.py
xlsxcreator/excel_convertor.py
xlsx_creator-1.4.0.dist-info/METADATA
xlsx_creator-1.4.0.dist-info/WHEEL
xlsx_creator-1.4.0.dist-info/top_level.txt
xlsx_creator-1.4.0.dist-info/RECORD
