Metadata-Version: 2.4
Name: xlsx-creator
Version: 1.4.0
Summary: 엑셀 생성기 from dictionary
Author-email: Yu Jeonghoon <jeonghoon@jnghn.xyz>
License: MIT License
Project-URL: Homepage, https://github.com/moning02004/xlsx-creator
Project-URL: Bug Tracker, https://github.com/moning02004/xlsx-creator/issues
Requires-Python: >=3.8
License-File: LICENSE
License-File: NOTICE
Requires-Dist: XlsxWriter>=3.0.0
Dynamic: license-file
